LICENSE.txt
MANIFEST.in
README.md
requirements.txt
setup.py
testlog.txt
paegan/__init__.py
paegan/resources/shoreline/global/10m_land.dbf
paegan/resources/shoreline/global/10m_land.prj
paegan/resources/shoreline/global/10m_land.shp
paegan/resources/shoreline/global/10m_land.shx
paegan/transport/__init__.py
paegan/transport/bathymetry.py
paegan/transport/exceptions.py
paegan/transport/export.py
paegan/transport/forcers.py
paegan/transport/parallel_manager.py
paegan/transport/shoreline.py
paegan/transport/controllers/__init__.py
paegan/transport/controllers/base.py
paegan/transport/controllers/cached.py
paegan/transport/controllers/distributed.py
paegan/transport/controllers/ipython.py
paegan/transport/models/__init__.py
paegan/transport/models/base_model.py
paegan/transport/models/behavior.py
paegan/transport/models/transport.py
paegan/transport/models/behaviors/__init__.py
paegan/transport/models/behaviors/capability.py
paegan/transport/models/behaviors/diel.py
paegan/transport/models/behaviors/lifestage.py
paegan/transport/models/behaviors/settlement.py
paegan/transport/models/behaviors/taxis.py
paegan/transport/particles/__init__.py
paegan/transport/particles/particle.py
paegan/transport/utils/__init__.py
paegan/transport/utils/asastochastic.py
paegan/transport/utils/asasuncycles.py
paegan/transport/utils/asatransport.py
paegan_transport.egg-info/PKG-INFO
paegan_transport.egg-info/SOURCES.txt
paegan_transport.egg-info/dependency_links.txt
paegan_transport.egg-info/namespace_packages.txt
paegan_transport.egg-info/requires.txt
paegan_transport.egg-info/top_level.txt