Metadata-Version: 1.1
Name: paegan-transport
Version: 1.0.4
Summary: Particle transport packages for the Paegan library
Home-page: https://github.com/axiom-data-science/paegan-transport
Author: Kyle Wilcox
Author-email: kyle@axiomdatascience.com
License: GPLv3
Platform: UNKNOWN
Classifier: Development Status :: 3 - Alpha
Classifier: Intended Audience :: Developers
Classifier: Intended Audience :: Science/Research
Classifier: License :: OSI Approved :: GNU General Public License v3 (GPLv3)
Classifier: Operating System :: POSIX :: Linux
Classifier: Programming Language :: Python
Classifier: Topic :: Scientific/Engineering
